virtshell_commands
