Metadata-Version: 1.1
Name: virtshell-commands
Version: 1.0.2
Summary: Shell commands for VirtShell
Home-page: https://github.com/janutechnology/VirtShell
Author: Carlos Alberto Llano R.
Author-email: carlos_llano@hotmail.com
License: MIT
Keywords: provisioning
Platform: UNKNOWN
Classifier: Development Status :: 3 - Alpha
Classifier: Intended Audience :: Developers
Classifier: Topic :: Software Development :: Build Tools
Classifier: License :: OSI Approved :: MIT License
Classifier: Programming Language :: Python :: 3
Classifier: Programming Language :: Python :: 3.2
Classifier: Programming Language :: Python :: 3.3
Classifier: Programming Language :: Python :: 3.4
